memofn/__init__.py
memofn/mvp.py
memofn/utils/__init__.py
memofn/utils/hashable.py
memofn-0.1.0.dist-info/LICENSE
memofn-0.1.0.dist-info/WHEEL
memofn-0.1.0.dist-info/METADATA
memofn-0.1.0.dist-info/RECORD
