Metadata-Version: 2.1
Name: memofn
Version: 0.1.0
Summary: A python library for memoizing functions for quick debugging/translations
Author: Moises Baltazar
Author-email: null@moisesb.com
Requires-Python: >=3.10,<4.0
Classifier: License :: OSI Approved :: MIT License
Classifier: Operating System :: OS Independent
Classifier: Programming Language :: Python :: 3
Classifier: Programming Language :: Python :: 3.10
Classifier: Programming Language :: Python :: 3.11
Classifier: Programming Language :: Python :: 3
